JunoMalacards/__init__.py
JunoMalacards/core.py
JunoMalacards/dow_html.py
JunoMalacards/get_ip.py
JunoMalacards/get_url.py
JunoMalacards-0.1.2.dist-info/METADATA
JunoMalacards-0.1.2.dist-info/WHEEL
JunoMalacards-0.1.2.dist-info/entry_points.txt
JunoMalacards-0.1.2.dist-info/top_level.txt
JunoMalacards-0.1.2.dist-info/RECORD
